td_ml_ps_stats_scan/__init__.py
td_ml_ps_stats_scan/scan_parent_segments.py
td_ml_ps_stats_scan-0.0.27.dist-info/licenses/LICENSE
td_ml_ps_stats_scan-0.0.27.dist-info/METADATA
td_ml_ps_stats_scan-0.0.27.dist-info/WHEEL
td_ml_ps_stats_scan-0.0.27.dist-info/top_level.txt
td_ml_ps_stats_scan-0.0.27.dist-info/RECORD
