Metadata-Version: 2.3
Name: td_ml_ps_stats_scan
Version: 0.0.27
Summary: Extract Parent Segment Stats
Author-email: Dilyan Kovachev <pruchka@gmail.com>
License: Copyright © 2022 Treasure Data, Inc. (or its affiliates). All rights reserved
Project-URL: Homepage, https://github.com/YOUR PROJECT REPO URL
Project-URL: Bug Tracker, https://github.com/YOUR PROJECT REPO URL
Classifier: Programming Language :: Python :: 3
Classifier: Operating System :: OS Independent
Requires-Python: >=3.8
License-File: LICENSE
Dynamic: license-file
